zarinpal/__init__.py
zarinpal/api.py
zarinpal/error_handling.py
zarinpal_payment_integration-0.0.1.dist-info/LICENSE
zarinpal_payment_integration-0.0.1.dist-info/METADATA
zarinpal_payment_integration-0.0.1.dist-info/WHEEL
zarinpal_payment_integration-0.0.1.dist-info/top_level.txt
zarinpal_payment_integration-0.0.1.dist-info/RECORD
