Metadata-Version: 2.1
Name: zarinpal-payment-integration
Version: 0.0.1
Summary: This Python package provides a simple interface for interacting with the ZarinPal payment gateway. It allows you to make payment requests, verify payments, and handle errors gracefully.
Home-page: https://github.com/hamidrezafarzin/zarinpal-payment-integration
Author: Hamidreza Farzin
Author-email: hamidfarzin1382@gmail.com
Project-URL: Author, https://github.com/hamidrezafarzin
Classifier: Programming Language :: Python :: 3
Classifier: License :: OSI Approved :: MIT License
Classifier: Operating System :: OS Independent
Requires-Python: >=3.7
License-File: LICENSE
Requires-Dist: requests
